{
  "$schema": "https://tree-sitter.github.io/tree-sitter/assets/schemas/grammar.schema.json",
  "name": "ink",
  "rules": {
    "program": {
      "type": "SEQ",
      "members": [
        {
          "type": "CHOICE",
          "members": [
            {
              "type": "SYMBOL",
              "name": "weave_body"
            },
            {
              "type": "BLANK"
            }
          ]
        },
        {
          "type": "REPEAT",
          "content": {
            "type": "CHOICE",
            "members": [
              {
                "type": "SYMBOL",
                "name": "knot"
              },
              {
                "type": "SYMBOL",
                "name": "function"
              }
            ]
          }
        }
      ]
    },
    "knot": {
      "type": "SEQ",
      "members": [
        {
          "type": "SYMBOL",
          "name": "knot_header"
        },
        {
          "type": "CHOICE",
          "members": [
            {
              "type": "SYMBOL",
              "name": "weave_body"
            },
            {
              "type": "BLANK"
            }
          ]
        },
        {
          "type": "REPEAT",
          "content": {
            "type": "SYMBOL",
            "name": "stitch"
          }
        }
      ]
    },
    "knot_header": {
      "type": "SEQ",
      "members": [
        {
          "type": "SYMBOL",
          "name": "knot_start"
        },
        {
          "type": "CHOICE",
          "members": [
            {
              "type": "PATTERN",
              "value": "=+"
            },
            {
              "type": "BLANK"
            }
          ]
        },
        {
          "type": "SYMBOL",
          "name": "identifier"
        },
        {
          "type": "CHOICE",
          "members": [
            {
              "type": "PATTERN",
              "value": "=+"
            },
            {
              "type": "BLANK"
            }
          ]
        },
        {
          "type": "SYMBOL",
          "name": "line_end"
        }
      ]
    },
    "stitch": {
      "type": "SEQ",
      "members": [
        {
          "type": "SYMBOL",
          "name": "stitch_header"
        },
        {
          "type": "SYMBOL",
          "name": "weave_body"
        }
      ]
    },
    "stitch_header": {
      "type": "SEQ",
      "members": [
        {
          "type": "SYMBOL",
          "name": "stitch_start"
        },
        {
          "type": "SYMBOL",
          "name": "identifier"
        },
        {
          "type": "SYMBOL",
          "name": "line_end"
        }
      ]
    },
    "weave_body": {
      "type": "PREC_RIGHT",
      "value": 0,
      "content": {
        "type": "REPEAT1",
        "content": {
          "type": "SYMBOL",
          "name": "weave_body_line"
        }
      }
    },
    "weave_body_line": {
      "type": "SEQ",
      "members": [
        {
          "type": "SYMBOL",
          "name": "body_start"
        },
        {
          "type": "CHOICE",
          "members": [
            {
              "type": "CHOICE",
              "members": [
                {
                  "type": "SYMBOL",
                  "name": "choice_text"
                },
                {
                  "type": "SYMBOL",
                  "name": "code_text"
                },
                {
                  "type": "SYMBOL",
                  "name": "dialog_text"
                }
              ]
            },
            {
              "type": "BLANK"
            }
          ]
        },
        {
          "type": "SYMBOL",
          "name": "line_end"
        }
      ]
    },
    "function": {
      "type": "SEQ",
      "members": [
        {
          "type": "SYMBOL",
          "name": "function_header"
        },
        {
          "type": "SYMBOL",
          "name": "function_body"
        }
      ]
    },
    "function_header": {
      "type": "SEQ",
      "members": [
        {
          "type": "SYMBOL",
          "name": "function_start"
        },
        {
          "type": "CHOICE",
          "members": [
            {
              "type": "PATTERN",
              "value": "=+"
            },
            {
              "type": "BLANK"
            }
          ]
        },
        {
          "type": "SYMBOL",
          "name": "identifier"
        },
        {
          "type": "CHOICE",
          "members": [
            {
              "type": "SYMBOL",
              "name": "arguments"
            },
            {
              "type": "BLANK"
            }
          ]
        },
        {
          "type": "CHOICE",
          "members": [
            {
              "type": "PATTERN",
              "value": "=+"
            },
            {
              "type": "BLANK"
            }
          ]
        },
        {
          "type": "SYMBOL",
          "name": "line_end"
        }
      ]
    },
    "function_body": {
      "type": "PREC_RIGHT",
      "value": 0,
      "content": {
        "type": "REPEAT1",
        "content": {
          "type": "SYMBOL",
          "name": "function_body_line"
        }
      }
    },
    "function_body_line": {
      "type": "SEQ",
      "members": [
        {
          "type": "SYMBOL",
          "name": "body_start"
        },
        {
          "type": "CHOICE",
          "members": [
            {
              "type": "CHOICE",
              "members": [
                {
                  "type": "SYMBOL",
                  "name": "code_text"
                },
                {
                  "type": "SYMBOL",
                  "name": "dialog_text"
                }
              ]
            },
            {
              "type": "BLANK"
            }
          ]
        },
        {
          "type": "SYMBOL",
          "name": "line_end"
        }
      ]
    },
    "arguments": {
      "type": "SEQ",
      "members": [
        {
          "type": "PATTERN",
          "value": "\\("
        },
        {
          "type": "SYMBOL",
          "name": "identifier"
        },
        {
          "type": "REPEAT",
          "content": {
            "type": "SEQ",
            "members": [
              {
                "type": "PATTERN",
                "value": ","
              },
              {
                "type": "SYMBOL",
                "name": "identifier"
              }
            ]
          }
        },
        {
          "type": "CHOICE",
          "members": [
            {
              "type": "PATTERN",
              "value": ","
            },
            {
              "type": "BLANK"
            }
          ]
        },
        {
          "type": "PATTERN",
          "value": "\\)"
        }
      ]
    },
    "choice_text": {
      "type": "SEQ",
      "members": [
        {
          "type": "SYMBOL",
          "name": "choice_mark"
        },
        {
          "type": "SYMBOL",
          "name": "text"
        },
        {
          "type": "CHOICE",
          "members": [
            {
              "type": "SYMBOL",
              "name": "divert"
            },
            {
              "type": "BLANK"
            }
          ]
        }
      ]
    },
    "choice_mark": {
      "type": "REPEAT1",
      "content": {
        "type": "PATTERN",
        "value": "[\\+\\*]"
      }
    },
    "code_text": {
      "type": "SEQ",
      "members": [
        {
          "type": "PATTERN",
          "value": "~"
        },
        {
          "type": "SYMBOL",
          "name": "text"
        }
      ]
    },
    "dialog_text": {
      "type": "SEQ",
      "members": [
        {
          "type": "SYMBOL",
          "name": "text"
        },
        {
          "type": "CHOICE",
          "members": [
            {
              "type": "SYMBOL",
              "name": "divert"
            },
            {
              "type": "BLANK"
            }
          ]
        }
      ]
    },
    "text": {
      "type": "REPEAT1",
      "content": {
        "type": "CHOICE",
        "members": [
          {
            "type": "SYMBOL",
            "name": "vocabular"
          },
          {
            "type": "SYMBOL",
            "name": "other"
          }
        ]
      }
    },
    "divert": {
      "type": "SEQ",
      "members": [
        {
          "type": "SYMBOL",
          "name": "arrow"
        },
        {
          "type": "SYMBOL",
          "name": "identifier"
        }
      ]
    },
    "other": {
      "type": "PATTERN",
      "value": "[^\\s\\n\\r\\p{L}_]+"
    },
    "vocabular": {
      "type": "PATTERN",
      "value": "[\\p{L}_-]+"
    },
    "identifier": {
      "type": "PATTERN",
      "value": "[\\p{L}_]+"
    }
  },
  "extras": [
    {
      "type": "PATTERN",
      "value": "\\s"
    }
  ],
  "conflicts": [],
  "precedences": [],
  "externals": [
    {
      "type": "SYMBOL",
      "name": "arrow"
    },
    {
      "type": "SYMBOL",
      "name": "body_start"
    },
    {
      "type": "SYMBOL",
      "name": "stitch_start"
    },
    {
      "type": "SYMBOL",
      "name": "knot_start"
    },
    {
      "type": "SYMBOL",
      "name": "function_start"
    },
    {
      "type": "SYMBOL",
      "name": "line_end"
    }
  ],
  "inline": [],
  "supertypes": []
}
